aimodelshare/README.md
aimodelshare/__init__.py
aimodelshare/aimsonnx.py
aimodelshare/api.py
aimodelshare/auth.py
aimodelshare/aws.py
aimodelshare/aws_client.py
aimodelshare/base_image.py
aimodelshare/bucketpolicy.py
aimodelshare/containerisation.py
aimodelshare/containerization.py
aimodelshare/custom_eval_metrics.py
aimodelshare/deploy_custom_lambda.py
aimodelshare/exceptions.py
aimodelshare/generatemodelapi.py
aimodelshare/leaderboard.py
aimodelshare/model.py
aimodelshare/modeluser.py
aimodelshare/playground.py
aimodelshare/postprocessormodules.py
aimodelshare/preprocessormodules.py
aimodelshare/readme.md
aimodelshare/reproducibility.py
aimodelshare/tools.py
aimodelshare/utils.py
aimodelshare/color_mappings/color_mapping_keras.csv
aimodelshare/color_mappings/color_mapping_pytorch.csv
aimodelshare/containerization_templates/Dockerfile.txt
aimodelshare/containerization_templates/Dockerfile_PySpark.txt
aimodelshare/containerization_templates/buildspec.txt
aimodelshare/containerization_templates/lambda_function.txt
aimodelshare/custom_approach/__init__.py
aimodelshare/custom_approach/lambda_function.py
aimodelshare/data_sharing/__init__.py
aimodelshare/data_sharing/download_data.py
aimodelshare/data_sharing/share_data.py
aimodelshare/data_sharing/utils.py
aimodelshare/data_sharing/data_sharing_templates/Dockerfile.txt
aimodelshare/data_sharing/data_sharing_templates/__init__.py
aimodelshare/data_sharing/data_sharing_templates/buildspec.txt
aimodelshare/data_sharing/data_sharing_templates/codebuild_policies.txt
aimodelshare/data_sharing/data_sharing_templates/codebuild_trust_relationship.txt
aimodelshare/documentation/Makefile
aimodelshare/documentation/make.bat
aimodelshare/documentation/requirements.txt
aimodelshare/documentation/karma_sphinx_theme/__init__.py
aimodelshare/documentation/karma_sphinx_theme/_version.py
aimodelshare/documentation/karma_sphinx_theme/breadcrumbs.html
aimodelshare/documentation/karma_sphinx_theme/layout.html
aimodelshare-0.5.77.dist-info/licenses/LICENSE
aimodelshare-0.5.77.dist-info/METADATA
aimodelshare-0.5.77.dist-info/WHEEL
aimodelshare-0.5.77.dist-info/top_level.txt
aimodelshare-0.5.77.dist-info/RECORD
