Metadata-Version: 2.4
Name: aimodelshare
Version: 0.5.77
Summary: Deploy locally saved machine learning models to a live REST API and integrated dashboard.
Author-email: Michael Parrott <mikedparrott@modelshare.ai>
License: 
Keywords: machine-learning,deployment,api,onnx,tensorflow,pytorch
Classifier: Programming Language :: Python :: 3
Classifier: License :: Other/Proprietary License
Classifier: Operating System :: OS Independent
Requires-Python: >=3.10
License-File: LICENSE
Requires-Dist: numpy>=1.23.0
Requires-Dist: pandas>=1.5.0
Requires-Dist: requests
Requires-Dist: urllib3
Requires-Dist: boto3
Requires-Dist: onnx
Requires-Dist: onnxmltools
Requires-Dist: onnxruntime
Requires-Dist: skl2onnx
Requires-Dist: tf2onnx
Requires-Dist: scikit-learn>=1.2.0
Requires-Dist: scikeras
Requires-Dist: shortuuid
Requires-Dist: Pympler
Requires-Dist: wget
Requires-Dist: PyJWT[crypto]<3,>=2.8
Requires-Dist: pydot
Requires-Dist: regex
Requires-Dist: psutil
Requires-Dist: dill
Requires-Dist: IPython
Provides-Extra: visual
Requires-Dist: graphviz; extra == "visual"
Provides-Extra: tensorflow
Requires-Dist: tensorflow==2.19.0; extra == "tensorflow"
Requires-Dist: keras2onnx; extra == "tensorflow"
Provides-Extra: pytorch
Requires-Dist: torch; extra == "pytorch"
Provides-Extra: ui
Requires-Dist: gradio>=4.0.0; extra == "ui"
Provides-Extra: full
Requires-Dist: tensorflow==2.19.0; extra == "full"
Requires-Dist: keras2onnx; extra == "full"
Requires-Dist: torch; extra == "full"
Requires-Dist: graphviz; extra == "full"
Requires-Dist: gradio>=4.0.0; extra == "full"
Provides-Extra: test
Requires-Dist: pytest; extra == "test"
Requires-Dist: pytest-cov; extra == "test"
Dynamic: license-file
